THIRD_PARTY_LICENSES
qrlyzer/__init__.py
qrlyzer/__init__.pyi
qrlyzer/py.typed
qrlyzer/qrlyzer.cpython-312-darwin.so
qrlyzer-0.2.8.dist-info/METADATA
qrlyzer-0.2.8.dist-info/WHEEL
qrlyzer-0.2.8.dist-info/licenses/LICENSE
qrlyzer-0.2.8.dist-info/RECORD
