Metadata-Version: 2.4
Name: qrlyzer
Version: 0.2.8
Classifier: Programming Language :: Rust
Classifier: Operating System :: OS Independent
Classifier: Intended Audience :: Developers
Classifier: Programming Language :: Python :: 3.10
Classifier: Programming Language :: Python :: 3.11
Classifier: Programming Language :: Python :: 3.12
Classifier: Programming Language :: Python :: 3.13
Classifier: Programming Language :: Python :: 3.14
Classifier: Programming Language :: Python :: Implementation :: CPython
Classifier: Programming Language :: Python :: Implementation :: PyPy
Classifier: Topic :: Software Development :: Libraries
License-File: LICENSE
Summary: qrlyzer is a lightweight Python module for reading QR codes from images.
Maintainer-email: Nikolai Ugelvik <nikolai@netlife.no>
Requires-Python: >=3.10
Project-URL: Changelog, https://github.com/netlifeas/qrlyzer/releases
Project-URL: Issues, https://github.com/netlifeas/qrlyzer/issues
Project-URL: Repository, https://github.com/netlifeas/qrlyzer.git
